setup.cfg
setup.py
Releasy.egg-info/PKG-INFO
Releasy.egg-info/SOURCES.txt
Releasy.egg-info/dependency_links.txt
Releasy.egg-info/requires.txt
Releasy.egg-info/top_level.txt
releasy/__init__.py
releasy/log.py
releasy/publisher.py
releasy/repo.py
scripts/releasy