Metadata-Version: 1.1
Name: Releasy
Version: 0.1
Summary: Releasy its a release notes manager for your projects
Home-page: https://github.com/andrefsp/releasy/
Author: Andre da Palma
Author-email: andrefsp@gmail.com
License: UNKNOWN
Keywords: git,management,release
Platform: UNKNOWN
Classifier: License :: OSI Approved :: MIT License
Classifier: Programming Language :: Python :: 3.4
Classifier: Programming Language :: Python :: 3.5
Classifier: Topic :: Software Development :: Libraries :: Python Modules
Requires: gitpython(==1.0.1)
